<annotation>
	<folder>images</folder>
	<filename>new130.png</filename>
	<path>C:\Users\xiaotudui\Desktop\HelmetDataset-NoLabels\train\images\new130.png</path>
	<source>
		<database>Unknown</database>
	</source>
	<size>
		<width>381</width>
		<height>572</height>
		<depth>3</depth>
	</size>
	<segmented>0</segmented>
	<object>
		<name>number</name>
		<pose>Unspecified</pose>
		<truncated>0</truncated>
		<difficult>0</difficult>
		<bndbox>
			<xmin>54</xmin>
			<ymin>362</ymin>
			<xmax>156</xmax>
			<ymax>385</ymax>
		</bndbox>
	</object>
	<object>
		<name>motor</name>
		<pose>Unspecified</pose>
		<truncated>0</truncated>
		<difficult>0</difficult>
		<bndbox>
			<xmin>27</xmin>
			<ymin>177</ymin>
			<xmax>355</xmax>
			<ymax>570</ymax>
		</bndbox>
	</object>
	<object>
		<name>no helmet</name>
		<pose>Unspecified</pose>
		<truncated>0</truncated>
		<difficult>0</difficult>
		<bndbox>
			<xmin>168</xmin>
			<ymin>160</ymin>
			<xmax>222</xmax>
			<ymax>221</ymax>
		</bndbox>
	</object>
	<object>
		<name>no helmet</name>
		<pose>Unspecified</pose>
		<truncated>0</truncated>
		<difficult>0</difficult>
		<bndbox>
			<xmin>186</xmin>
			<ymin>30</ymin>
			<xmax>257</xmax>
			<ymax>124</ymax>
		</bndbox>
	</object>
</annotation>
