<annotation>
	<folder>images</folder>
	<filename>new11.png</filename>
	<path>C:\Users\xiaotudui\Desktop\自定义数据集-未包含标注\train\images\new11.png</path>
	<source>
		<database>Unknown</database>
	</source>
	<size>
		<width>538</width>
		<height>456</height>
		<depth>3</depth>
	</size>
	<segmented>0</segmented>
	<object>
		<name>number</name>
		<pose>Unspecified</pose>
		<truncated>0</truncated>
		<difficult>0</difficult>
		<bndbox>
			<xmin>70</xmin>
			<ymin>300</ymin>
			<xmax>140</xmax>
			<ymax>337</ymax>
		</bndbox>
	</object>
	<object>
		<name>motor</name>
		<pose>Unspecified</pose>
		<truncated>0</truncated>
		<difficult>0</difficult>
		<bndbox>
			<xmin>64</xmin>
			<ymin>220</ymin>
			<xmax>321</xmax>
			<ymax>446</ymax>
		</bndbox>
	</object>
	<object>
		<name>with helmet</name>
		<pose>Unspecified</pose>
		<truncated>0</truncated>
		<difficult>0</difficult>
		<bndbox>
			<xmin>180</xmin>
			<ymin>31</ymin>
			<xmax>268</xmax>
			<ymax>106</ymax>
		</bndbox>
	</object>
</annotation>
