<annotation>
	<folder>images</folder>
	<filename>new76.png</filename>
	<path>C:\Users\xiaotudui\Desktop\HelmetDataset-YOLO\train\images\new76.png</path>
	<source>
		<database>Unknown</database>
	</source>
	<size>
		<width>602</width>
		<height>673</height>
		<depth>3</depth>
	</size>
	<segmented>0</segmented>
	<object>
		<name>no helmet</name>
		<pose>Unspecified</pose>
		<truncated>0</truncated>
		<difficult>0</difficult>
		<bndbox>
			<xmin>285</xmin>
			<ymin>126</ymin>
			<xmax>342</xmax>
			<ymax>215</ymax>
		</bndbox>
	</object>
	<object>
		<name>number</name>
		<pose>Unspecified</pose>
		<truncated>0</truncated>
		<difficult>0</difficult>
		<bndbox>
			<xmin>219</xmin>
			<ymin>421</ymin>
			<xmax>328</xmax>
			<ymax>446</ymax>
		</bndbox>
	</object>
	<object>
		<name>motor</name>
		<pose>Unspecified</pose>
		<truncated>0</truncated>
		<difficult>0</difficult>
		<bndbox>
			<xmin>122</xmin>
			<ymin>282</ymin>
			<xmax>427</xmax>
			<ymax>670</ymax>
		</bndbox>
	</object>
</annotation>
